LICENSE
README.md
setup.py
bin/findres
findres/__init__.py
findres/analyze.py
findres/custom_formats.py
findres/plot.py
findres/read.py
findres/utils.py
findres/write.py
findres.egg-info/PKG-INFO
findres.egg-info/SOURCES.txt
findres.egg-info/dependency_links.txt
findres.egg-info/requires.txt
findres.egg-info/top_level.txt