Metadata-Version: 2.1
Name: findres
Version: 0.3.0
Summary: Repeating earthquake discovery using cross-correlation and differential arrival times
Home-page: https://github.com/msugan/pyres
Author: Monica Sugan, Stefano Campanella
Author-email: msugan@inogs.it, scampanella@inogs.it
License: UNKNOWN
Platform: UNKNOWN
Classifier: Programming Language :: Python :: 3
Classifier: License :: OSI Approved :: MIT License
Classifier: Operating System :: OS Independent
Requires-Python: ~=3.8
License-File: LICENSE
